bolift/__init__.py
bolift/aqfxns.py
bolift/asktell.py
bolift/asktellGPR.py
bolift/asktellNearestNeighbor.py
bolift/asktellRidgeRegression.py
bolift/asktellfinetuning.py
bolift/llm_model.py
bolift/pool.py
bolift/tool.py
bolift/version.py
bolift-0.2.1.dist-info/METADATA
bolift-0.2.1.dist-info/WHEEL
bolift-0.2.1.dist-info/top_level.txt
bolift-0.2.1.dist-info/RECORD
