Metadata-Version: 2.1
Name: bolift
Version: 0.2.1
Summary: BayesOPT with LIFT
Home-page: https://github.com/whitead/bolift
Author: Andrew White
Author-email: andrew.white@rochester.edu
License: MIT
Classifier: Programming Language :: Python :: 3
Classifier: License :: OSI Approved :: MIT License
Classifier: Operating System :: OS Independent
Requires-Dist: numpy
Requires-Dist: langchain
Requires-Dist: openai
Requires-Dist: faiss-cpu
Requires-Dist: scipy
Requires-Dist: pandas
Requires-Dist: tiktoken
Provides-Extra: gpr
Requires-Dist: scikit-learn ; extra == 'gpr'
Requires-Dist: torch ; extra == 'gpr'
Requires-Dist: botorch ; extra == 'gpr'
Requires-Dist: gpytorch ; extra == 'gpr'
